LICENSE.md
eetlijst/__init__.py
python_eetlijst-2.0.0.dist-info/LICENSE.md
python_eetlijst-2.0.0.dist-info/WHEEL
python_eetlijst-2.0.0.dist-info/METADATA
python_eetlijst-2.0.0.dist-info/RECORD
