Metadata-Version: 2.1
Name: python-eetlijst
Version: 2.0.0
Summary: Unofficial Python API to interface with Eetlijst.nl
Home-page: https://github.com/basilfx/python-eetlijst
License: GPL-3.0
Author: Bas Stottelaar
Author-email: basstottelaar@gmail.com
Requires-Python: >=3.10,<4.0
Classifier: Development Status :: 5 - Production/Stable
Classifier: Intended Audience :: Developers
Classifier: License :: OSI Approved :: GNU General Public License v3 (GPLv3)
Classifier: Programming Language :: Python :: 3
Classifier: Programming Language :: Python :: 3.10
Classifier: Programming Language :: Python :: 3.11
Classifier: Topic :: Home Automation
Classifier: Topic :: System :: Networking
Requires-Dist: beautifulsoup4 (>=4.11.1,<5.0.0)
Requires-Dist: pytz (>=2022.6,<2023.0)
Requires-Dist: requests (>=2.28.1,<3.0.0)
Project-URL: Repository, https://github.com/basilfx/python-eetlijst
